MANIFEST.in
requirements.txt
setup.py
cloudstore/__init__.py
cloudstore/config.py
cloudstore/domains.py
cloudstore/errors.py
cloudstore/factory.py
cloudstore/store.py
cloudstore/backends/__init__.py
cloudstore/backends/bcs/__init__.py
cloudstore/backends/oss/__init__.py
cloudstore/backends/oss/assembly.py
cloudstore/backends/oss/handler.py
cloudstore/backends/qiniu/__init__.py
cloudstore/backends/s3/__init__.py
cloudstore/backends/s3/assembly.py
cloudstore/oss/__init__.py
cloudstore/oss/oss_api.py
cloudstore/oss/oss_fs.py
cloudstore/oss/oss_sample.py
cloudstore/oss/oss_util.py
cloudstore/oss/oss_xml_handler.py
cloudstore/oss/pkg_info.py
cloudstore/pybcs/__init__.py
cloudstore/pybcs/bcs.py
cloudstore/pybcs/bucket.py
cloudstore/pybcs/common.py
cloudstore/pybcs/httpc.py
cloudstore/pybcs/object.py
cloudstore/qbox/MultipartPostHandler.py
cloudstore/qbox/__init__.py
cloudstore/qbox/config.py
cloudstore/qbox/digestoauth.py
cloudstore/qbox/eu.py
cloudstore/qbox/eu_demo.py
cloudstore/qbox/fileop.py
cloudstore/qbox/fileop_demo.py
cloudstore/qbox/put_demo.py
cloudstore/qbox/rs.py
cloudstore/qbox/rs_demo.py
cloudstore/qbox/rscli.py
cloudstore/qbox/simpleoauth2.py
cloudstore/qbox/uptoken.py
cloudstore/qbox/uptoken_demo.py
cloudstore/qbox/wm_demo.py
libstorages.egg-info/PKG-INFO
libstorages.egg-info/SOURCES.txt
libstorages.egg-info/dependency_links.txt
libstorages.egg-info/not-zip-safe
libstorages.egg-info/top_level.txt
tests/backends/__init__.py
tests/backends/bcs.py
tests/backends/oss/__init__.py
tests/backends/oss/mock_assembly.py
tests/backends/oss/mock_handler.py
tests/backends/oss/mock_oss_api.py
tests/backends/oss/test_adapter.py
tests/backends/oss/test_assembly.py
tests/backends/oss/test_handler.py
tests/backends/oss/test_stube.py
tests/backends/s3/__init__.py
tests/backends/s3/test_stube.py